notiontree/__init__.py
notiontree/hierarchy.py
notion_tree-0.0.1a4.dist-info/LICENSE
notion_tree-0.0.1a4.dist-info/METADATA
notion_tree-0.0.1a4.dist-info/WHEEL
notion_tree-0.0.1a4.dist-info/top_level.txt
notion_tree-0.0.1a4.dist-info/RECORD
