Metadata-Version: 2.1
Name: notion-tree
Version: 0.0.1a4
Summary: UNKNOWN
Home-page: https://github.com/aureplop/notion-tree
Author: Aurélien Delobelle
Author-email: aurelien.delobelle@gmail.com
License: MIT
Project-URL: Source, https://github.com/aureplop/notion-tree
Project-URL: Tracker, https://github.com/aureplop/notion-tree/issues
Keywords: notion structure hierarchy export import sync
Platform: UNKNOWN
Classifier: Development Status :: 3 - Alpha
Classifier: Programming Language :: Python :: 3
Classifier: License :: OSI Approved :: MIT License
Classifier: Operating System :: OS Independent
Requires-Python: >=3.6
